{"config":{"output_file":null,"full_docs":false,"pub_only":false,"reachable_only":false,"distro_crate":false,"signatures":false,"borrow_data":false},"version":"0.19.1","compilation":{"directory":"/Users/ncontinanza/Projects/The-Rust-Programming-Language/patterns","program":"/Users/ncontinanza/.rustup/toolchains/stable-aarch64-apple-darwin/bin/rls","arguments":[],"output":"/Users/ncontinanza/Projects/The-Rust-Programming-Language/patterns/target/rls/debug/deps/libpatterns-63086ede52ae77e7.rmeta"},"prelude":{"crate_id":{"name":"patterns","disambiguator":[6030297864346925965,0]},"crate_root":"src","external_crates":[{"file_name":"/Users/ncontinanza/Projects/The-Rust-Programming-Language/patterns/src/main.rs","num":1,"id":{"name":"std","disambiguator":[17588522495838200792,0]}},{"file_name":"/Users/ncontinanza/Projects/The-Rust-Programming-Language/patterns/src/main.rs","num":2,"id":{"name":"core","disambiguator":[8278583129772197859,0]}},{"file_name":"/Users/ncontinanza/Projects/The-Rust-Programming-Language/patterns/src/main.rs","num":3,"id":{"name":"compiler_builtins","disambiguator":[14913712660212466740,0]}},{"file_name":"/Users/ncontinanza/Projects/The-Rust-Programming-Language/patterns/src/main.rs","num":4,"id":{"name":"rustc_std_workspace_core","disambiguator":[169217235897429410,0]}},{"file_name":"/Users/ncontinanza/Projects/The-Rust-Programming-Language/patterns/src/main.rs","num":5,"id":{"name":"alloc","disambiguator":[3895911861305942990,0]}},{"file_name":"/Users/ncontinanza/Projects/The-Rust-Programming-Language/patterns/src/main.rs","num":6,"id":{"name":"libc","disambiguator":[9813622304494305451,0]}},{"file_name":"/Users/ncontinanza/Projects/The-Rust-Programming-Language/patterns/src/main.rs","num":7,"id":{"name":"unwind","disambiguator":[12767531755122486811,0]}},{"file_name":"/Users/ncontinanza/Projects/The-Rust-Programming-Language/patterns/src/main.rs","num":8,"id":{"name":"cfg_if","disambiguator":[11042621516499360545,0]}},{"file_name":"/Users/ncontinanza/Projects/The-Rust-Programming-Language/patterns/src/main.rs","num":9,"id":{"name":"miniz_oxide","disambiguator":[12900059087317885891,0]}},{"file_name":"/Users/ncontinanza/Projects/The-Rust-Programming-Language/patterns/src/main.rs","num":10,"id":{"name":"rustc_std_workspace_alloc","disambiguator":[2276627185568532740,0]}},{"file_name":"/Users/ncontinanza/Projects/The-Rust-Programming-Language/patterns/src/main.rs","num":11,"id":{"name":"adler","disambiguator":[6031887558045411683,0]}},{"file_name":"/Users/ncontinanza/Projects/The-Rust-Programming-Language/patterns/src/main.rs","num":12,"id":{"name":"hashbrown","disambiguator":[1726102652612607821,0]}},{"file_name":"/Users/ncontinanza/Projects/The-Rust-Programming-Language/patterns/src/main.rs","num":13,"id":{"name":"std_detect","disambiguator":[14945886052262342754,0]}},{"file_name":"/Users/ncontinanza/Projects/The-Rust-Programming-Language/patterns/src/main.rs","num":14,"id":{"name":"rustc_demangle","disambiguator":[329292103076465253,0]}},{"file_name":"/Users/ncontinanza/Projects/The-Rust-Programming-Language/patterns/src/main.rs","num":15,"id":{"name":"addr2line","disambiguator":[471687133851620970,0]}},{"file_name":"/Users/ncontinanza/Projects/The-Rust-Programming-Language/patterns/src/main.rs","num":16,"id":{"name":"gimli","disambiguator":[605306301665063266,0]}},{"file_name":"/Users/ncontinanza/Projects/The-Rust-Programming-Language/patterns/src/main.rs","num":17,"id":{"name":"object","disambiguator":[11032979542905123237,0]}},{"file_name":"/Users/ncontinanza/Projects/The-Rust-Programming-Language/patterns/src/main.rs","num":18,"id":{"name":"memchr","disambiguator":[18407608818322377071,0]}},{"file_name":"/Users/ncontinanza/Projects/The-Rust-Programming-Language/patterns/src/main.rs","num":19,"id":{"name":"panic_unwind","disambiguator":[7683813092153219624,0]}}],"span":{"file_name":"src/main.rs","byte_start":0,"byte_end":912,"line_start":1,"line_end":35,"column_start":1,"column_end":2}},"imports":[],"defs":[{"kind":"Mod","id":{"krate":0,"index":0},"span":{"file_name":"src/main.rs","byte_start":0,"byte_end":912,"line_start":1,"line_end":35,"column_start":1,"column_end":2},"name":"","qualname":"::","value":"src/main.rs","parent":null,"children":[{"krate":0,"index":1},{"krate":0,"index":2},{"krate":0,"index":3}],"decl_id":null,"docs":"","sig":null,"attributes":[]},{"kind":"Function","id":{"krate":0,"index":3},"span":{"file_name":"src/main.rs","byte_start":3,"byte_end":7,"line_start":1,"line_end":1,"column_start":4,"column_end":8},"name":"main","qualname":"::main","value":"fn main()","parent":null,"children":[],"decl_id":null,"docs":"","sig":null,"attributes":[]},{"kind":"Local","id":{"krate":0,"index":3489660931},"span":{"file_name":"src/main.rs","byte_start":20,"byte_end":34,"line_start":2,"line_end":2,"column_start":9,"column_end":23},"name":"favorite_color","qualname":"favorite_color$HirId { owner: DefId(0:3 ~ patterns[53af]::main), local_id: 11 }","value":"std::option::Option<&str>","parent":null,"children":[],"decl_id":null,"docs":"","sig":null,"attributes":[]},{"kind":"Local","id":{"krate":0,"index":4026531843},"span":{"file_name":"src/main.rs","byte_start":65,"byte_end":75,"line_start":3,"line_end":3,"column_start":9,"column_end":19},"name":"is_tuesday","qualname":"is_tuesday$HirId { owner: DefId(0:3 ~ patterns[53af]::main), local_id: 15 }","value":"bool","parent":null,"children":[],"decl_id":null,"docs":"","sig":null,"attributes":[]},{"kind":"Local","id":{"krate":0,"index":1476395011},"span":{"file_name":"src/main.rs","byte_start":93,"byte_end":96,"line_start":4,"line_end":4,"column_start":9,"column_end":12},"name":"age","qualname":"age$HirId { owner: DefId(0:3 ~ patterns[53af]::main), local_id: 26 }","value":"std::result::Result<u8, std::num::ParseIntError>","parent":null,"children":[],"decl_id":null,"docs":"","sig":null,"attributes":[]},{"kind":"Local","id":{"krate":0,"index":3271557123},"span":{"file_name":"src/main.rs","byte_start":614,"byte_end":619,"line_start":20,"line_end":20,"column_start":13,"column_end":18},"name":"stack","qualname":"stack$HirId { owner: DefId(0:3 ~ patterns[53af]::main), local_id: 195 }","value":"std::vec::Vec<i32>","parent":null,"children":[],"decl_id":null,"docs":"","sig":null,"attributes":[]},{"kind":"Local","id":{"krate":0,"index":3900702723},"span":{"file_name":"src/main.rs","byte_start":777,"byte_end":778,"line_start":30,"line_end":30,"column_start":9,"column_end":10},"name":"v","qualname":"v$HirId { owner: DefId(0:3 ~ patterns[53af]::main), local_id: 279 }","value":"std::vec::Vec<char>","parent":null,"children":[],"decl_id":null,"docs":"","sig":null,"attributes":[]},{"kind":"Local","id":{"krate":0,"index":2021654531},"span":{"file_name":"src/main.rs","byte_start":812,"byte_end":817,"line_start":32,"line_end":32,"column_start":10,"column_end":15},"name":"index","qualname":"index$HirId { owner: DefId(0:3 ~ patterns[53af]::main), local_id: 286 }","value":"usize","parent":null,"children":[],"decl_id":null,"docs":"","sig":null,"attributes":[]},{"kind":"Local","id":{"krate":0,"index":4169138179},"span":{"file_name":"src/main.rs","byte_start":819,"byte_end":824,"line_start":32,"line_end":32,"column_start":17,"column_end":22},"name":"value","qualname":"value$HirId { owner: DefId(0:3 ~ patterns[53af]::main), local_id: 287 }","value":"&char","parent":null,"children":[],"decl_id":null,"docs":"","sig":null,"attributes":[]}],"impls":[],"refs":[{"kind":"Type","span":{"file_name":"src/main.rs","byte_start":36,"byte_end":42,"line_start":2,"line_end":2,"column_start":25,"column_end":31},"ref_id":{"krate":2,"index":39667}},{"kind":"Type","span":{"file_name":"src/main.rs","byte_start":51,"byte_end":55,"line_start":2,"line_end":2,"column_start":40,"column_end":44},"ref_id":{"krate":2,"index":39669}},{"kind":"Type","span":{"file_name":"src/main.rs","byte_start":98,"byte_end":104,"line_start":4,"line_end":4,"column_start":14,"column_end":20},"ref_id":{"krate":2,"index":39794}},{"kind":"Function","span":{"file_name":"src/main.rs","byte_start":119,"byte_end":124,"line_start":4,"line_end":4,"column_start":35,"column_end":40},"ref_id":{"krate":2,"index":12868}},{"kind":"Variable","span":{"file_name":"src/main.rs","byte_start":154,"byte_end":168,"line_start":6,"line_end":6,"column_start":26,"column_end":40},"ref_id":{"krate":0,"index":3489660931}},{"kind":"Type","span":{"file_name":"src/main.rs","byte_start":140,"byte_end":144,"line_start":6,"line_end":6,"column_start":12,"column_end":16},"ref_id":{"krate":2,"index":39671}},{"kind":"Variable","span":{"file_name":"src/main.rs","byte_start":240,"byte_end":245,"line_start":7,"line_end":7,"column_start":70,"column_end":75},"ref_id":{"krate":0,"index":3087007747}},{"kind":"Variable","span":{"file_name":"src/main.rs","byte_start":262,"byte_end":272,"line_start":8,"line_end":8,"column_start":15,"column_end":25},"ref_id":{"krate":0,"index":4026531843}},{"kind":"Variable","span":{"file_name":"src/main.rs","byte_start":346,"byte_end":349,"line_start":10,"line_end":10,"column_start":29,"column_end":32},"ref_id":{"krate":0,"index":1476395011}},{"kind":"Type","span":{"file_name":"src/main.rs","byte_start":336,"byte_end":338,"line_start":10,"line_end":10,"column_start":19,"column_end":21},"ref_id":{"krate":2,"index":39797}},{"kind":"Variable","span":{"file_name":"src/main.rs","byte_start":363,"byte_end":366,"line_start":11,"line_end":11,"column_start":12,"column_end":15},"ref_id":{"krate":0,"index":3321888771}},{"kind":"Function","span":{"file_name":"src/main.rs","byte_start":627,"byte_end":630,"line_start":20,"line_end":20,"column_start":26,"column_end":29},"ref_id":{"krate":5,"index":7096}},{"kind":"Type","span":{"file_name":"src/main.rs","byte_start":622,"byte_end":625,"line_start":20,"line_end":20,"column_start":21,"column_end":24},"ref_id":{"krate":5,"index":7089}},{"kind":"Function","span":{"file_name":"src/main.rs","byte_start":645,"byte_end":649,"line_start":22,"line_end":22,"column_start":11,"column_end":15},"ref_id":{"krate":5,"index":7170}},{"kind":"Variable","span":{"file_name":"src/main.rs","byte_start":639,"byte_end":644,"line_start":22,"line_end":22,"column_start":5,"column_end":10},"ref_id":{"krate":0,"index":3271557123}},{"kind":"Function","span":{"file_name":"src/main.rs","byte_start":664,"byte_end":668,"line_start":23,"line_end":23,"column_start":11,"column_end":15},"ref_id":{"krate":5,"index":7170}},{"kind":"Variable","span":{"file_name":"src/main.rs","byte_start":658,"byte_end":663,"line_start":23,"line_end":23,"column_start":5,"column_end":10},"ref_id":{"krate":0,"index":3271557123}},{"kind":"Function","span":{"file_name":"src/main.rs","byte_start":683,"byte_end":687,"line_start":24,"line_end":24,"column_start":11,"column_end":15},"ref_id":{"krate":5,"index":7170}},{"kind":"Variable","span":{"file_name":"src/main.rs","byte_start":677,"byte_end":682,"line_start":24,"line_end":24,"column_start":5,"column_end":10},"ref_id":{"krate":0,"index":3271557123}},{"kind":"Function","span":{"file_name":"src/main.rs","byte_start":725,"byte_end":728,"line_start":26,"line_end":26,"column_start":33,"column_end":36},"ref_id":{"krate":5,"index":7171}},{"kind":"Variable","span":{"file_name":"src/main.rs","byte_start":719,"byte_end":724,"line_start":26,"line_end":26,"column_start":27,"column_end":32},"ref_id":{"krate":0,"index":3271557123}},{"kind":"Type","span":{"file_name":"src/main.rs","byte_start":707,"byte_end":711,"line_start":26,"line_end":26,"column_start":15,"column_end":19},"ref_id":{"krate":2,"index":39671}},{"kind":"Variable","span":{"file_name":"src/main.rs","byte_start":756,"byte_end":759,"line_start":27,"line_end":27,"column_start":24,"column_end":27},"ref_id":{"krate":0,"index":452984835}},{"kind":"Function","span":{"file_name":"src/main.rs","byte_start":838,"byte_end":847,"line_start":32,"line_end":32,"column_start":36,"column_end":45},"ref_id":{"krate":2,"index":8019}},{"kind":"Function","span":{"file_name":"src/main.rs","byte_start":831,"byte_end":835,"line_start":32,"line_end":32,"column_start":29,"column_end":33},"ref_id":{"krate":2,"index":11644}},{"kind":"Variable","span":{"file_name":"src/main.rs","byte_start":829,"byte_end":830,"line_start":32,"line_end":32,"column_start":27,"column_end":28},"ref_id":{"krate":0,"index":3900702723}},{"kind":"Variable","span":{"file_name":"src/main.rs","byte_start":890,"byte_end":895,"line_start":33,"line_end":33,"column_start":39,"column_end":44},"ref_id":{"krate":0,"index":4169138179}},{"kind":"Variable","span":{"file_name":"src/main.rs","byte_start":897,"byte_end":902,"line_start":33,"line_end":33,"column_start":46,"column_end":51},"ref_id":{"krate":0,"index":2021654531}}],"macro_refs":[],"relations":[]}